issue.py
issue-0.1.0.dist-info/WHEEL
issue-0.1.0.dist-info/METADATA
issue-0.1.0.dist-info/LICENSE
issue-0.1.0.dist-info/RECORD
