Metadata-Version: 2.1
Name: issue
Version: 0.1.0
Summary: Filter logs by name. Allow Unix shell style wildcards.
License: UNKNOWN
Author-email: abersheeran <me@abersheeran.com>
Requires-Python: >=3.7
Project-URL: homepage, https://github.com/abersheeran/issue
